{
  "lastRun": "2026-07-07T14:47:50.392Z",
  "bulletins": [
    {
      "key": "us",
      "url": "https://travel.state.gov/content/travel/en/legal/visa-law0/visa-bulletin.html",
      "hash": "f9f5d75adab85b47910480c45efde5009d4b566cc8cc4ad83af45f51494d4e02",
      "lastChangedAt": "2026-07-01T12:38:40.226Z",
      "lastCheckedAt": "2026-07-07T14:45:16.788Z",
      "lastStatus": "unchanged"
    },
    {
      "key": "ca",
      "url": "https://www.canada.ca/en/immigration-refugees-citizenship/services/immigrate-canada/express-entry/submit-profile/rounds-invitations.html",
      "monitorUrl": "https://api.io.canada.ca/io-server/gc/news/en/v2?dept=departmentofcitizenshipandimmigration&sort=publishedDate&orderBy=desc&pick=50&format=atom",
      "hash": "471fbd74a0850cbaa4afb11474f79947755ef696fee0132ef53d5912ab68108b",
      "lastChangedAt": "2026-07-06T20:02:57.885Z",
      "lastCheckedAt": "2026-07-07T14:45:18.188Z",
      "lastStatus": "unchanged"
    },
    {
      "key": "br",
      "url": "https://www.gov.br/pf/pt-br/assuntos/imigracao/inicio",
      "geoProxy": true,
      "hash": "a71b2c23d2190a4b0cf734719d56dff99a96cac58fa637892847e5fa72b57e4b",
      "lastChangedAt": "2026-07-07T14:45:19.354Z",
      "lastCheckedAt": "2026-07-07T14:45:19.354Z",
      "lastStatus": "changed"
    },
    {
      "key": "de",
      "url": "https://www.bamf.de/EN/Themen/Statistik/Asylzahlen/asylzahlen-node.html",
      "monitorUrl": "https://www.destatis.de/EN/Themes/Society-Environment/Population/Migration-Integration/_node.html",
      "geoProxy": true,
      "hash": "2ead1729783d59d1aa7bf95162041b24c3177399de883699fc7036b56b0aafd1",
      "lastChangedAt": "2026-06-23T11:21:29.962Z",
      "lastCheckedAt": "2026-07-07T14:45:20.980Z",
      "lastStatus": "unchanged"
    },
    {
      "key": "at",
      "url": "https://www.migration.gv.at/en/",
      "hash": "db79e0fafbaeeb3e0c927ae37d152ad01cd69ffa0f4cb8d0668e8be8466997a6",
      "lastChangedAt": "2026-05-21T03:48:58.288Z",
      "lastCheckedAt": "2026-07-07T14:45:23.164Z",
      "lastStatus": "unchanged"
    },
    {
      "key": "be",
      "url": "https://www.ibz.be",
      "hash": "4fae71266dafe07cb81e19d6ad39401c183c4b6889922cef50659cda01e7e699",
      "lastChangedAt": "2026-07-07T14:45:25.344Z",
      "lastCheckedAt": "2026-07-07T14:45:25.344Z",
      "lastStatus": "changed"
    },
    {
      "key": "bg",
      "url": "https://aref.government.bg/?explnum=21",
      "geoProxy": true,
      "hash": "1032198403c8612e3a4b86c158879ec6cbdd173d7a4fef15e289ee1628eeff3a",
      "lastChangedAt": "2026-07-07T11:12:01.762Z",
      "lastCheckedAt": "2026-07-07T14:45:27.434Z",
      "lastStatus": "unchanged"
    },
    {
      "key": "cy",
      "url": "https://www.moi.gov.cy/",
      "hash": "b66a3711eb174f90dd06a81f487a530fc8b87b0463fca021f21c32ad25127b98",
      "lastChangedAt": "2026-07-06T16:54:07.882Z",
      "lastCheckedAt": "2026-07-07T14:45:29.245Z",
      "lastStatus": "unchanged"
    },
    {
      "key": "hr",
      "url": "https://mup.gov.hr/",
      "hash": "cfb235d21e749703e4910787c4ecb18c43500c063c575ac9687ad16e03ca4556",
      "lastChangedAt": "2026-07-02T17:52:59.357Z",
      "lastCheckedAt": "2026-07-07T14:45:32.480Z",
      "lastStatus": "unchanged"
    },
    {
      "key": "dk",
      "url": "https://www.nyidanmark.dk/en-GB",
      "hash": "5742e03b9db1dcf8fc9d2fdf92eb69ac21214a7da4817e5d2dc6ebe81ccb3630",
      "lastChangedAt": "2026-07-03T10:40:45.619Z",
      "lastCheckedAt": "2026-07-07T14:45:33.763Z",
      "lastStatus": "unchanged"
    },
    {
      "key": "sk",
      "url": "https://www.minv.sk/",
      "hash": "d3030fbb555a7d5f335faee09b8becd70e7d531fb3820fbda0ce1e216f449b58",
      "lastChangedAt": "2026-07-07T11:12:18.370Z",
      "lastCheckedAt": "2026-07-07T14:45:35.363Z",
      "lastStatus": "unchanged"
    },
    {
      "key": "si",
      "url": "https://www.gov.si/en/",
      "hash": "65742ef29b5a9a3ac48ce7d2dafdc83a933e655bd0ab28d73f4b4ed4f6177edd",
      "lastChangedAt": "2026-07-02T14:11:28.439Z",
      "lastCheckedAt": "2026-07-07T14:45:36.900Z",
      "lastStatus": "unchanged"
    },
    {
      "key": "es",
      "url": "https://www.inclusion.gob.es/web/migraciones",
      "monitorUrl": "https://www.boe.es/rss/canal.php?c=ultimas10dias",
      "geoProxy": true,
      "hash": "e3b0c44298fc1c149afbf4c8996fb92427ae41e4649b934ca495991b7852b855",
      "lastChangedAt": "2026-05-27T08:18:28.063Z",
      "lastCheckedAt": "2026-07-07T14:45:38.162Z",
      "lastStatus": "unchanged"
    },
    {
      "key": "ee",
      "url": "https://www.politsei.ee/en",
      "monitorUrl": "https://www.eesti.ee/en/",
      "geoProxy": true,
      "hash": "f2e641de3afb1e67a693a6ccc8a0045b0f5311dbdf034f42f7a7a1ec847910ef",
      "lastChangedAt": "2026-06-17T11:05:00.730Z",
      "lastCheckedAt": "2026-07-07T14:45:39.704Z",
      "lastStatus": "unchanged"
    },
    {
      "key": "fi",
      "url": "https://migri.fi/en/home",
      "hash": "cf89a4b2dd5adfa3354c24809810410a392bef32b05326750d591066e7485638",
      "lastChangedAt": "2026-07-07T14:45:41.171Z",
      "lastCheckedAt": "2026-07-07T14:45:41.171Z",
      "lastStatus": "changed"
    },
    {
      "key": "fr",
      "url": "https://www.immigration.interieur.gouv.fr/actualites",
      "monitorUrl": "https://www.ofii.fr/actualites/",
      "geoProxy": true,
      "hash": "66286b932b30c185e21b551b02fe0f7be9af95fdf104363d9f0dfd6cb6849b9b",
      "lastChangedAt": "2026-05-21T03:49:31.743Z",
      "lastCheckedAt": "2026-07-07T14:45:43.566Z",
      "lastStatus": "unchanged"
    },
    {
      "key": "gr",
      "url": "https://migration.gov.gr/en/",
      "hash": "1d26d2f94caf174e4c36a29c9c8007ec181e11ba312c8a5a9e0fdc85f07566b1",
      "lastChangedAt": "2026-07-07T14:45:44.989Z",
      "lastCheckedAt": "2026-07-07T14:45:44.989Z",
      "lastStatus": "changed"
    },
    {
      "key": "nl",
      "url": "https://ind.nl/en",
      "hash": "9256ada0fa9fc4e0278a9d0ea546c16a16bfd4f68bc1585bafd60be4cdd09591",
      "lastChangedAt": "2026-07-07T14:45:46.482Z",
      "lastCheckedAt": "2026-07-07T14:45:46.482Z",
      "lastStatus": "changed"
    },
    {
      "key": "hu",
      "url": "https://oif.gov.hu/",
      "hash": "ca73d3c2292aa0838b40cb62eecb78c1146a11376a59161742aced0a74a2c857",
      "lastChangedAt": "2026-07-07T14:45:47.765Z",
      "lastCheckedAt": "2026-07-07T14:45:47.765Z",
      "lastStatus": "changed"
    },
    {
      "key": "is",
      "url": "https://utl.is/index.php/en/",
      "hash": "d09a7528c99cde2b93bd48429616d52847d9a716b30db0b1104ff23a5772947d",
      "lastChangedAt": "2026-07-07T14:45:50.650Z",
      "lastCheckedAt": "2026-07-07T14:45:50.650Z",
      "lastStatus": "changed"
    },
    {
      "key": "no",
      "url": "https://www.udi.no/en/",
      "hash": "69b42a074c60bc8553aa6ffeb1c3e54e5c6716bbae07be83d8811747a205df76",
      "lastChangedAt": "2026-07-03T14:16:42.025Z",
      "lastCheckedAt": "2026-07-07T14:45:52.824Z",
      "lastStatus": "unchanged"
    },
    {
      "key": "ru",
      "url": "https://www.kdmid.ru/",
      "hash": "273b8c82c0c1a168877f91508ea4e1213e4c87eefdae48cd3fd609d84a4b090d",
      "lastChangedAt": "2026-07-02T10:45:12.675Z",
      "lastCheckedAt": "2026-07-07T14:45:54.189Z",
      "lastStatus": "unchanged"
    },
    {
      "key": "nz",
      "url": "https://www.immigration.govt.nz/",
      "hash": "1e43b14b84ba4ca0e2a14d801814805a338d562ac2abd25a6b6c77e0c6fc8c2b",
      "lastChangedAt": "2026-07-07T14:45:55.880Z",
      "lastCheckedAt": "2026-07-07T14:45:55.880Z",
      "lastStatus": "changed"
    },
    {
      "key": "ie",
      "url": "https://www.irishimmigration.ie/",
      "hash": "0f9c4550d352b0e80f1213c5e655159f2148a29631a12c48e68185ff69632c6d",
      "lastChangedAt": "2026-07-07T11:12:58.007Z",
      "lastCheckedAt": "2026-07-07T14:45:58.573Z",
      "lastStatus": "unchanged"
    },
    {
      "key": "it",
      "url": "https://questure.poliziadistato.it/stranieri/",
      "hash": "45a9df3a5cc3d12d287bc5cc863cece1189100a74c33fbb4db073c2a5c902334",
      "lastChangedAt": "2026-06-26T12:15:36.438Z",
      "lastCheckedAt": "2026-07-07T14:45:59.591Z",
      "lastStatus": "unchanged"
    },
    {
      "key": "lv",
      "url": "https://www.pmlp.gov.lv/en",
      "hash": "a6988c73eac71cc47d582a6dd7f30aa6da6d0aa17d04554b592f6e1d4162d3f8",
      "lastChangedAt": "2026-07-07T14:46:00.878Z",
      "lastCheckedAt": "2026-07-07T14:46:00.878Z",
      "lastStatus": "changed"
    },
    {
      "key": "lt",
      "url": "https://migracija.lt/en/",
      "hash": "1e7e0a7f80d9380ce4010738ec718116150f8082f2c724444704ff18ba3a8f60",
      "lastChangedAt": "2026-06-22T18:15:02.550Z",
      "lastCheckedAt": "2026-07-07T14:46:02.649Z",
      "lastStatus": "error_http_502"
    },
    {
      "key": "lu",
      "url": "https://guichet.public.lu/en/citoyens/immigration.html",
      "hash": "e9a2c38986650eb5ebb34c55a9a4ff0b583d7c16fc469add3bb1e7f97587d6ff",
      "lastChangedAt": "2026-07-07T14:47:23.769Z",
      "lastCheckedAt": "2026-07-07T14:47:23.769Z",
      "lastStatus": "changed"
    },
    {
      "key": "mt",
      "url": "https://www.identita.gov.mt/",
      "hash": "b6539d769ca8b133a68714787e4127cf39ab4782a0b807ebd74c3276d910625f",
      "lastChangedAt": "2026-07-07T03:48:18.952Z",
      "lastCheckedAt": "2026-07-07T14:47:25.301Z",
      "lastStatus": "unchanged"
    },
    {
      "key": "pl",
      "url": "https://www.gov.pl/web/udsc-en",
      "hash": "a887c3101d6f774785a52f58082f31a0c7dee981f1411e41900f91a14df92760",
      "lastChangedAt": "2026-06-15T18:46:22.619Z",
      "lastCheckedAt": "2026-07-07T14:47:29.169Z",
      "lastStatus": "unchanged"
    },
    {
      "key": "pt",
      "url": "https://aima.gov.pt/pt",
      "monitorUrl": "https://dre.pt/dre/feeds/diariodarepublica",
      "geoProxy": true,
      "hash": "fbbf82525bd1c6b7faaf7b38f847543f2b590f9bfab5efd909ce7f52db294924",
      "lastChangedAt": "2026-05-27T08:19:05.704Z",
      "lastCheckedAt": "2026-07-07T14:47:30.868Z",
      "lastStatus": "unchanged"
    },
    {
      "key": "uk",
      "url": "https://www.gov.uk/government/collections/migration-statistics",
      "hash": "ad93ca79c4a978318f531a3e89b4f31c4bdb30a8bd973892d1a37bdcc357e42b",
      "lastChangedAt": "2026-07-07T14:47:32.239Z",
      "lastCheckedAt": "2026-07-07T14:47:32.239Z",
      "lastStatus": "changed"
    },
    {
      "key": "cz",
      "url": "https://www.mvcr.cz/mvcren/",
      "hash": "2daccd5143476bf928882cbe5c3a7d2d5cf52697200af0bc990c79abd96f474a",
      "lastChangedAt": "2026-07-07T14:47:33.638Z",
      "lastCheckedAt": "2026-07-07T14:47:33.638Z",
      "lastStatus": "changed"
    },
    {
      "key": "ro",
      "url": "https://igi.mai.gov.ro/en",
      "geoProxy": true,
      "hash": "6acbdaedfcd6b70b1c74e4a2402deb7f23227b5f703ae3d748d6aade885f279e",
      "lastChangedAt": "2026-07-07T14:47:35.663Z",
      "lastCheckedAt": "2026-07-07T14:47:35.663Z",
      "lastStatus": "changed"
    },
    {
      "key": "se",
      "url": "https://www.migrationsverket.se/English.html",
      "hash": "212abe241159794b9bb9e988a29264b2c490f3900da1044aad4332c63a7ee5eb",
      "lastChangedAt": "2026-07-07T14:47:38.209Z",
      "lastCheckedAt": "2026-07-07T14:47:38.209Z",
      "lastStatus": "changed"
    },
    {
      "key": "ch",
      "url": "https://www.sem.admin.ch/sem/en/home.html",
      "hash": "3d58ada297a8227737db4abdc25a999ca03f4a283dc66b7a3c4a77e962a37b1d",
      "lastChangedAt": "2026-07-07T14:47:40.048Z",
      "lastCheckedAt": "2026-07-07T14:47:40.048Z",
      "lastStatus": "changed"
    },
    {
      "key": "ae",
      "url": "https://icp.gov.ae/en/",
      "hash": "5072eb9e43194b471f3fdbef41bc5a85207804588d18d62ff547fc106fb7bed8",
      "lastChangedAt": "2026-07-07T14:47:41.648Z",
      "lastCheckedAt": "2026-07-07T14:47:41.648Z",
      "lastStatus": "changed"
    },
    {
      "key": "au",
      "url": "https://immi.homeaffairs.gov.au/visas/working-in-australia/skillselect/invitation-rounds",
      "hash": "fd872eb7ddbbae7981386a73013d2acbca059829258d4772d4f5dc178ee1cffc",
      "lastChangedAt": "2026-07-07T14:47:45.130Z",
      "lastCheckedAt": "2026-07-07T14:47:45.130Z",
      "lastStatus": "changed"
    },
    {
      "key": "cn",
      "url": "https://en.nia.gov.cn/",
      "hash": "f2d425cc21040252f5cd3c9f82f5b1526c3266135190a34dac219cd0927f86d4",
      "lastChangedAt": "2026-06-29T04:20:24.614Z",
      "lastCheckedAt": "2026-07-07T14:47:46.279Z",
      "lastStatus": "unchanged"
    },
    {
      "key": "jp",
      "url": "https://www.moj.go.jp/isa/index.html",
      "hash": "491a3589ee0032228ee4e6d6a493eb757afdfe5ac0d9a73e484404377f7781b5",
      "lastChangedAt": "2026-07-06T13:51:26.533Z",
      "lastCheckedAt": "2026-07-07T14:47:49.292Z",
      "lastStatus": "unchanged"
    }
  ]
}
