{
  "lastRun": "2026-05-27T08:35:33.668Z",
  "bulletins": [
    {
      "key": "us",
      "url": "https://travel.state.gov/content/travel/en/legal/visa-law0/visa-bulletin.html",
      "hash": "e56098ca58a41cb8c6593f85ca5eca46cc691b8ec6ac3a3d05aecccac38194e3",
      "lastChangedAt": "2026-05-21T18:15:36.031Z",
      "lastCheckedAt": "2026-05-27T08:32:47.225Z",
      "lastStatus": "unchanged"
    },
    {
      "key": "ca",
      "url": "https://www.canada.ca/en/immigration-refugees-citizenship/services/immigrate-canada/express-entry/submit-profile/rounds-invitations.html",
      "monitorUrl": "https://api.io.canada.ca/io-server/gc/news/en/v2?dept=departmentofcitizenshipandimmigration&sort=publishedDate&orderBy=desc&pick=50&format=atom",
      "hash": "ea9cb7232755abab74b1713efba28657f40fe414740ced08f9e344f17fcee4d0",
      "lastChangedAt": "2026-05-25T17:21:43.770Z",
      "lastCheckedAt": "2026-05-27T08:32:48.327Z",
      "lastStatus": "unchanged"
    },
    {
      "key": "br",
      "url": "https://www.gov.br/pf/pt-br/assuntos/imigracao/inicio",
      "hash": "875069dd5969decd43376e3fb037138549f65107e8ea8068b4dc904894b3f75c",
      "lastChangedAt": "2026-05-26T19:28:37.383Z",
      "lastCheckedAt": "2026-05-27T08:32:49.201Z",
      "lastStatus": "unchanged"
    },
    {
      "key": "de",
      "url": "https://www.bamf.de/EN/Themen/Statistik/Asylzahlen/asylzahlen-node.html",
      "monitorUrl": "https://www.destatis.de/EN/Themes/Society-Environment/Population/Migration-Integration/_node.html",
      "geoProxy": true,
      "hash": "83b00a17ea300abea58c53f98d6ba7368387c21ee8f9e5157fa862215b694c43",
      "lastChangedAt": "2026-05-21T03:48:55.595Z",
      "lastCheckedAt": "2026-05-27T08:32:50.804Z",
      "lastStatus": "unchanged"
    },
    {
      "key": "at",
      "url": "https://www.migration.gv.at/en/",
      "hash": "db79e0fafbaeeb3e0c927ae37d152ad01cd69ffa0f4cb8d0668e8be8466997a6",
      "lastChangedAt": "2026-05-21T03:48:58.288Z",
      "lastCheckedAt": "2026-05-27T08:32:52.178Z",
      "lastStatus": "unchanged"
    },
    {
      "key": "be",
      "url": "https://dofi.ibz.be/en",
      "hash": "ae2e4d253957d774ae49f573c07ee9ee429a3de6072f8056f995f06e5ec5839f",
      "lastChangedAt": "2026-05-27T07:18:30.795Z",
      "lastCheckedAt": "2026-05-27T08:32:54.395Z",
      "lastStatus": "error_fetch failed"
    },
    {
      "key": "bg",
      "url": "https://aref.government.bg/?explnum=21",
      "geoProxy": true,
      "hash": "e2974e26c5ae0f35518d3856b8e2dcaf43d57d614608845d9adbc15218a925b9",
      "lastChangedAt": "2026-05-27T07:18:32.227Z",
      "lastCheckedAt": "2026-05-27T08:33:02.128Z",
      "lastStatus": "error_fetch failed"
    },
    {
      "key": "cy",
      "url": "https://www.moi.gov.cy/",
      "hash": "e2a8c8f014035643d3bdba5914dbc1b7b1383620ebd673982a5bde420ddc65fa",
      "lastChangedAt": "2026-05-26T19:29:22.073Z",
      "lastCheckedAt": "2026-05-27T08:33:40.411Z",
      "lastStatus": "unchanged"
    },
    {
      "key": "hr",
      "url": "https://mup.gov.hr/",
      "hash": "70b11eb5bf38419d7b74363e1d0d6dd06e9e3bf0f56b4ac399f9d1716a4a16eb",
      "lastChangedAt": "2026-05-26T19:29:25.374Z",
      "lastCheckedAt": "2026-05-27T08:33:45.345Z",
      "lastStatus": "unchanged"
    },
    {
      "key": "dk",
      "url": "https://www.nyidanmark.dk/en-GB",
      "hash": "1f3cc6c716389e439a2c451c028e74ee4d2f6bfada2a0c3dede43e573b85dbf5",
      "lastChangedAt": "2026-05-27T08:18:22.100Z",
      "lastCheckedAt": "2026-05-27T08:33:46.596Z",
      "lastStatus": "unchanged"
    },
    {
      "key": "sk",
      "url": "https://www.minv.sk/",
      "hash": "35f8d42f9d2498c30036dae9859d718d9da82cd07f291197687a4ecd2de6a3b3",
      "lastChangedAt": "2026-05-27T08:33:48.382Z",
      "lastCheckedAt": "2026-05-27T08:33:48.382Z",
      "lastStatus": "changed"
    },
    {
      "key": "si",
      "url": "https://www.gov.si/en/",
      "hash": "287ef17d9a9c4ac65bb2464402cbd3b634e7a1c8a74de3d084a0e3234fbe58b4",
      "lastChangedAt": "2026-05-21T03:49:14.238Z",
      "lastCheckedAt": "2026-05-27T08:34:00.205Z",
      "lastStatus": "unchanged"
    },
    {
      "key": "es",
      "url": "https://www.inclusion.gob.es/web/migraciones",
      "monitorUrl": "https://www.boe.es/rss/canal.php?c=ultimas10dias",
      "geoProxy": true,
      "hash": "e3b0c44298fc1c149afbf4c8996fb92427ae41e4649b934ca495991b7852b855",
      "lastChangedAt": "2026-05-27T08:18:28.063Z",
      "lastCheckedAt": "2026-05-27T08:34:02.217Z",
      "lastStatus": "error_fetch failed"
    },
    {
      "key": "ee",
      "url": "https://www.politsei.ee/en",
      "monitorUrl": "https://www.eesti.ee/en/",
      "geoProxy": true,
      "hash": "0b516a2f298ee86e18558e410e6c223039ea825af98c59d75951fa1c11093c76",
      "lastChangedAt": "2026-05-27T08:21:45.296Z",
      "lastCheckedAt": "2026-05-27T08:34:40.505Z",
      "lastStatus": "unchanged"
    },
    {
      "key": "fi",
      "url": "https://migri.fi/en/home",
      "hash": "13a562ae9d94f671ff1c9ef7e06517235be8283a98f19c8a528241747098a282",
      "lastChangedAt": "2026-05-27T08:34:41.966Z",
      "lastCheckedAt": "2026-05-27T08:34:41.966Z",
      "lastStatus": "changed"
    },
    {
      "key": "fr",
      "url": "https://www.immigration.interieur.gouv.fr/actualites",
      "monitorUrl": "https://www.ofii.fr/actualites/",
      "geoProxy": true,
      "hash": "66286b932b30c185e21b551b02fe0f7be9af95fdf104363d9f0dfd6cb6849b9b",
      "lastChangedAt": "2026-05-21T03:49:31.743Z",
      "lastCheckedAt": "2026-05-27T08:34:43.463Z",
      "lastStatus": "unchanged"
    },
    {
      "key": "gr",
      "url": "https://migration.gov.gr/en/",
      "hash": "d937c1276818ea78dba11d8af9fb33603c0191a222767f015d63f2b649df5f94",
      "lastChangedAt": "2026-05-27T08:34:44.839Z",
      "lastCheckedAt": "2026-05-27T08:34:44.839Z",
      "lastStatus": "changed"
    },
    {
      "key": "nl",
      "url": "https://ind.nl/en",
      "hash": "408d33538ddced82c7b7506f6a23dd89b2bf18e8637885c9750e804ceebf3d8c",
      "lastChangedAt": "2026-05-27T08:18:37.739Z",
      "lastCheckedAt": "2026-05-27T08:34:46.356Z",
      "lastStatus": "unchanged"
    },
    {
      "key": "hu",
      "url": "https://oif.gov.hu/",
      "hash": "1616dc900b8beaf056faefdc2a4af439627b3ae4f814ac38e9a2bea990a717f0",
      "lastChangedAt": "2026-05-27T08:34:47.441Z",
      "lastCheckedAt": "2026-05-27T08:34:47.441Z",
      "lastStatus": "changed"
    },
    {
      "key": "is",
      "url": "https://utl.is/index.php/en/",
      "hash": "61531953a5260e2f1dd6176b9c511262b960829faa865c2d0bf2884c2782122e",
      "lastChangedAt": "2026-05-27T08:34:50.319Z",
      "lastCheckedAt": "2026-05-27T08:34:50.319Z",
      "lastStatus": "changed"
    },
    {
      "key": "no",
      "url": "https://www.udi.no/en/",
      "hash": "69b42a074c60bc8553aa6ffeb1c3e54e5c6716bbae07be83d8811747a205df76",
      "lastChangedAt": "2026-05-21T06:11:46.304Z",
      "lastCheckedAt": "2026-05-27T08:34:52.383Z",
      "lastStatus": "unchanged"
    },
    {
      "key": "ru",
      "url": "https://www.kdmid.ru/",
      "hash": "d23718b4121e8747e83a5c33aaddff46db0ad5d7ca27f9a61008b1f563515dd6",
      "lastChangedAt": "2026-05-21T18:16:19.186Z",
      "lastCheckedAt": "2026-05-27T08:34:53.618Z",
      "lastStatus": "unchanged"
    },
    {
      "key": "nz",
      "url": "https://www.immigration.govt.nz/",
      "hash": "80a33e78228350ab7a0fd703afee4e4bc3ffaf551f022b2799a701da9f3fe6e5",
      "lastChangedAt": "2026-05-27T08:34:55.229Z",
      "lastCheckedAt": "2026-05-27T08:34:55.229Z",
      "lastStatus": "changed"
    },
    {
      "key": "ie",
      "url": "https://www.irishimmigration.ie/",
      "hash": "53335f9b09e130754882b1b33029d0a40233c4ad7c32a2e45a22b7eab2857ee2",
      "lastChangedAt": "2026-05-27T08:34:58.028Z",
      "lastCheckedAt": "2026-05-27T08:34:58.028Z",
      "lastStatus": "changed"
    },
    {
      "key": "it",
      "url": "https://questure.poliziadistato.it/stranieri/",
      "hash": "965561566aee890da410e4253d178ac678dcf2c7c89057b11873dd3e460be39e",
      "lastChangedAt": "2026-05-22T17:30:22.521Z",
      "lastCheckedAt": "2026-05-27T08:34:59.087Z",
      "lastStatus": "unchanged"
    },
    {
      "key": "lv",
      "url": "https://www.pmlp.gov.lv/en",
      "hash": "9ce1ba2759a80ec74d7456c95ddd4fe320c5e8e5161a1ed50f2f5a4541286f8c",
      "lastChangedAt": "2026-05-27T08:35:00.244Z",
      "lastCheckedAt": "2026-05-27T08:35:00.244Z",
      "lastStatus": "changed"
    },
    {
      "key": "lt",
      "url": "https://migracija.lt/en/",
      "hash": "876ecc16fff9e53e46c9d7eca212f888960a989dccfae9809b69f9f19d16f8f7",
      "lastChangedAt": "2026-05-21T18:16:28.733Z",
      "lastCheckedAt": "2026-05-27T08:35:01.849Z",
      "lastStatus": "unchanged"
    },
    {
      "key": "lu",
      "url": "https://guichet.public.lu/en/citoyens/immigration.html",
      "hash": "1ccfe7b8266652681068451571e695810a3084cc86a4a2e676faecb0cabdbfb7",
      "lastChangedAt": "2026-05-27T08:35:03.679Z",
      "lastCheckedAt": "2026-05-27T08:35:03.679Z",
      "lastStatus": "changed"
    },
    {
      "key": "mt",
      "url": "https://www.identita.gov.mt/",
      "hash": "d0eab5747236bc7d5220e25554c872163e355f28ed88108fa38b9b44d1772ec3",
      "lastChangedAt": "2026-05-21T03:49:47.830Z",
      "lastCheckedAt": "2026-05-27T08:35:07.326Z",
      "lastStatus": "unchanged"
    },
    {
      "key": "pl",
      "url": "https://www.gov.pl/web/udsc-en",
      "hash": "6e8121ef1d7e2b2cb2323a4344251559bffd8dd155512fbaa7c0413913b144ac",
      "lastChangedAt": "2026-05-21T03:49:53.027Z",
      "lastCheckedAt": "2026-05-27T08:35:11.098Z",
      "lastStatus": "unchanged"
    },
    {
      "key": "pt",
      "url": "https://aima.gov.pt/pt",
      "monitorUrl": "https://dre.pt/dre/feeds/diariodarepublica",
      "geoProxy": true,
      "hash": "fbbf82525bd1c6b7faaf7b38f847543f2b590f9bfab5efd909ce7f52db294924",
      "lastChangedAt": "2026-05-27T08:19:05.704Z",
      "lastCheckedAt": "2026-05-27T08:35:12.548Z",
      "lastStatus": "unchanged"
    },
    {
      "key": "uk",
      "url": "https://www.gov.uk/government/collections/migration-statistics",
      "hash": "e47336c7f12bc434e80547eeed63147cc9af88dd06ccc0aa296568de056ef1de",
      "lastChangedAt": "2026-05-27T08:35:13.828Z",
      "lastCheckedAt": "2026-05-27T08:35:13.828Z",
      "lastStatus": "changed"
    },
    {
      "key": "cz",
      "url": "https://www.mvcr.cz/mvcren/",
      "hash": "be36d8560187e0a7416279e4a954423baa16574564df93436651e557fa7c7db2",
      "lastChangedAt": "2026-05-27T08:35:15.987Z",
      "lastCheckedAt": "2026-05-27T08:35:15.987Z",
      "lastStatus": "changed"
    },
    {
      "key": "ro",
      "url": "https://igi.mai.gov.ro/en",
      "geoProxy": true,
      "hash": "f9eb50820a85baf02d029c5d713b8fbd2096d142923284c40ea02769d395d45a",
      "lastChangedAt": "2026-05-27T08:22:23.902Z",
      "lastCheckedAt": "2026-05-27T08:35:18.220Z",
      "lastStatus": "error_http_403"
    },
    {
      "key": "se",
      "url": "https://www.migrationsverket.se/English.html",
      "hash": "78957a381bce143e65e1606574319d451356bea6a15ee0fbbcc608c9238ae76e",
      "lastChangedAt": "2026-05-27T08:35:20.333Z",
      "lastCheckedAt": "2026-05-27T08:35:20.333Z",
      "lastStatus": "changed"
    },
    {
      "key": "ch",
      "url": "https://www.sem.admin.ch/sem/en/home.html",
      "hash": "7f25ee7c3d3ca7e0c7b8da33c40684bbde6d41a865ace1fd72f302eff3994a7f",
      "lastChangedAt": "2026-05-26T19:30:55.991Z",
      "lastCheckedAt": "2026-05-27T08:35:22.280Z",
      "lastStatus": "unchanged"
    },
    {
      "key": "ae",
      "url": "https://icp.gov.ae/en/",
      "hash": "2442824c33e7a469e4aa659509ba362dfb25f83da583e9135754d91e54264555",
      "lastChangedAt": "2026-05-21T03:50:10.062Z",
      "lastCheckedAt": "2026-05-27T08:35:23.913Z",
      "lastStatus": "unchanged"
    },
    {
      "key": "au",
      "url": "https://immi.homeaffairs.gov.au/visas/working-in-australia/skillselect/invitation-rounds",
      "hash": "24e3d49a7ff31d4ed4a6f480a412f448474f217557f6c178fb17d38d78971dcd",
      "lastChangedAt": "2026-05-23T14:51:23.330Z",
      "lastCheckedAt": "2026-05-27T08:35:27.926Z",
      "lastStatus": "unchanged"
    },
    {
      "key": "cn",
      "url": "https://en.nia.gov.cn/",
      "hash": "766245c5ab322dc9178986fffc87bc310ad00c281add56bfe43cf9b60a6e9e17",
      "lastChangedAt": "2026-05-21T03:50:15.651Z",
      "lastCheckedAt": "2026-05-27T08:35:29.134Z",
      "lastStatus": "unchanged"
    },
    {
      "key": "jp",
      "url": "https://www.moj.go.jp/isa/index.html",
      "hash": "5c77b06ff8044e35035e94005e2df70847a5f0f29d7a54727a5d741a62c019a2",
      "lastChangedAt": "2026-05-25T17:23:50.258Z",
      "lastCheckedAt": "2026-05-27T08:35:32.602Z",
      "lastStatus": "unchanged"
    }
  ]
}
